breezeblocks/__init__.py
breezeblocks/database.py
breezeblocks/dml_builders.py
breezeblocks/exceptions.py
breezeblocks/pool.py
breezeblocks/query_builder.py
breezeblocks/sql/__init__.py
breezeblocks/sql/aggregates.py
breezeblocks/sql/column.py
breezeblocks/sql/column_collection.py
breezeblocks/sql/dml.py
breezeblocks/sql/expressions.py
breezeblocks/sql/join.py
breezeblocks/sql/operators.py
breezeblocks/sql/param_store.py
breezeblocks/sql/query.py
breezeblocks/sql/query_components.py
breezeblocks/sql/table.py
breezeblocks-0.2.4.dist-info/METADATA
breezeblocks-0.2.4.dist-info/RECORD
breezeblocks-0.2.4.dist-info/WHEEL
breezeblocks-0.2.4.dist-info/top_level.txt
