Metadata-Version: 2.1
Name: breezeblocks
Version: 0.2.4
Summary: A lightweight SQL Querying package.
Home-page: https://github.com/modimore/BreezeBlocks
Author: Quinn Mortimer
Author-email: quinn.e.mortimer@gmail.com
License: MIT
Platform: UNKNOWN
Classifier: Development Status :: 3 - Alpha
Classifier: Intended Audience :: Developers
Classifier: License :: OSI Approved :: MIT License
Classifier: Programming Language :: Python
Classifier: Programming Language :: Python :: 3
Classifier: Topic :: Database :: Front-Ends
Classifier: Operating System :: OS Independent
